romajitable/__init__.py
romajitable-0.0.1.dist-info/METADATA
romajitable-0.0.1.dist-info/RECORD
romajitable-0.0.1.dist-info/WHEEL
romajitable-0.0.1.dist-info/top_level.txt
