Metadata-Version: 2.1
Name: romajitable
Version: 0.0.1
Summary: A converted one small script from JS
Home-page: https://github.com/KotRikD/romajitable
Author: KotRik
Author-email: supadmin@kotrik.ru
License: UNKNOWN
Platform: UNKNOWN
Classifier: Programming Language :: Python :: 3
Classifier: License :: OSI Approved :: MIT License
Classifier: Operating System :: OS Independent
